{"config":{"_":[],"i":"./public/fonts/undertalebet.woff2","o":"./public/fonts/dist/ut_icon","t":"woff2","f":"ut_icon","FontPath":"./public/fonts/undertalebet.woff2","destFold":"./public/fonts/dist/ut_icon","threads":{},"fontPath":"./public/fonts/undertalebet.woff2"},"message":{"macintosh":{"256":{"en":"Aw0IcVFmWw=="},"copyright":{"en":"Copyright SwordsOfTheDamned 2017"},"fontFamily":{"en":"Phonetic Underbet"},"fontSubfamily":{"en":"Regular"},"uniqueID":{"en":"Phonetic Underbet"},"fullName":{"en":"Phonetic Underbet Regular"},"version":{"en":"Version 1.0"},"postScriptName":{"en":"PhoneticUnderbet"},"trademark":{"en":"FontStruct is a trademark of FontStruct.com"},"manufacturer":{"en":"https://fontstruct.com"},"designer":{"en":"SwordsOfTheDamned"},"description":{"en":"“Phonetic Underbet” was built with FontStruct"},"manufacturerURL":{"en":"https://fontstruct.com/fontstructions/show/1404825/phonetic-underbet"},"designerURL":{"en":"https://fontstruct.com/fontstructors/show/1442547/swordsofthedamned"},"license":{"en":"FontStruct Non-Commercial License"},"sampleText":{"en":"Five big quacking zephyrs jolt my wax bed"}},"windows":{"256":{"en":"Aw0IcVFmWw=="},"copyright":{"en":"Copyright SwordsOfTheDamned 2017"},"fontFamily":{"en":"Phonetic Underbet"},"fontSubfamily":{"en":"Regular"},"uniqueID":{"en":"Phonetic Underbet"},"fullName":{"en":"Phonetic Underbet Regular"},"version":{"en":"Version 1.0"},"postScriptName":{"en":"PhoneticUnderbet"},"trademark":{"en":"FontStruct is a trademark of FontStruct.com"},"manufacturer":{"en":"https://fontstruct.com"},"designer":{"en":"SwordsOfTheDamned"},"description":{"en":"“Phonetic Underbet” was built with FontStruct\n"},"manufacturerURL":{"en":"https://fontstruct.com/fontstructions/show/1404825/phonetic-underbet"},"designerURL":{"en":"https://fontstruct.com/fontstructors/show/1442547/swordsofthedamned"},"license":{"en":"FontStruct Non-Commercial License"},"sampleText":{"en":"Five big quacking zephyrs jolt my wax bed"}}},"data":[{"name":"ed952ce8e3fa3d92cda81125f0c0601c.woff2","size":7316,"chars":"U+20-7e,U+2018-2019,U+201c-201d","diff":0,"charsSize":99}],"record":[{"name":"LoadFile","start":145.5344,"end":169.9574},{"name":"transferFontType","start":170.7678,"end":172.4766},{"name":"loadHarbuzz","start":173.5283,"end":190.978},{"name":"initOpentype","start":192.1365,"end":192.7329},{"name":"createImage","start":193.2209,"end":193.3579},{"name":"getBasicMessage","start":193.7769,"end":194.9089},{"name":"PreSubset","start":195.3481,"end":282.1136},{"name":"subsetFont","start":283.1829,"end":487.3057},{"name":"outputCSS","start":488.2089,"end":491.4894},{"name":"outputHTML","start":492.2005,"end":506.9769}],"version":"4.15.0","env":{"envName":"node","runtime":{"name":"javascript","version":"22.14.0"},"os":{"name":"win32","version":"Windows 11 Home China","release":"10.0.26200"},"device":{"cpus":20,"locale":"zh-CN","architecture":"x64"},"createdTime":"Wed, 28 Jan 2026 00:53:21 GMT"},"bundleMessage":{"originLength":8004,"ttfLength":50012,"originSize":99,"bundledSize":99,"bundledTotalLength":7316},"css":{"family":"Phonetic Underbet","style":"normal","weight":400,"display":"swap"}}